hasnainkk/__init__.py
hasnainkk/core/__init__.py
hasnainkk/core/config.py
hasnainkk/core/dispatcher.py
hasnainkk/core/logger.py
hasnainkk/core/session_manager.py
hasnainkk/handlers/__init__.py
hasnainkk/handlers/base_handler.py
hasnainkk/handlers/ptb_handler.py
hasnainkk/handlers/pyro_handler.py
hasnainkk/handlers/pyrogram_handler.py
hasnainkk/utils/__init__.py
hasnainkk/utils/decorators.py
hasnainkk/utils/helpers.py
hasnainkk-1.2.dist-info/LICENSE
hasnainkk-1.2.dist-info/METADATA
hasnainkk-1.2.dist-info/WHEEL
hasnainkk-1.2.dist-info/top_level.txt
hasnainkk-1.2.dist-info/RECORD
