Metadata-Version: 2.1
Name: hasnainkk
Version: 1.2
Summary: Hybrid Pyrogram + python-telegram-bot (PTB) Telegram Bot Framework
Home-page: https://github.com/Endx0/hasnainkk
Author: Endx0
Author-email: lord_izana@yahoo.com
License: UNKNOWN
Platform: UNKNOWN
Classifier: Programming Language :: Python :: 3
Classifier: Programming Language :: Python :: 3.8
Classifier: License :: OSI Approved :: MIT License
Classifier: Operating System :: OS Independent
Classifier: Framework :: AsyncIO
Classifier: Topic :: Communications :: Chat
Requires-Python: >=3.8
Requires-Dist: pyrogram>=2.0.0
Requires-Dist: python-telegram-bot>=20.0
Requires-Dist: pyyaml>=6.0
